{"name":"super_sam:slope_clay_dark_green","param2":9.0,"x":40.0,"y":47.0,"z":58.0}
{"name":"super_sam:clay_dark_green","x":41.0,"y":47.0,"z":58.0}
{"name":"super_sam:clay_dark_green","x":42.0,"y":47.0,"z":58.0}
{"name":"super_sam:clay_dark_green","x":43.0,"y":47.0,"z":58.0}
{"name":"super_sam:slope_clay_dark_green","param2":12.0,"x":44.0,"y":47.0,"z":58.0}
{"name":"super_sam:slope_clay_dark_green","param2":16.0,"x":39.0,"y":47.0,"z":59.0}
{"name":"super_sam:slope_clay_dark_green","param2":9.0,"x":40.0,"y":46.0,"z":59.0}
{"name":"super_sam:clay_dark_green","x":40.0,"y":47.0,"z":59.0}
{"name":"super_sam:clay_dark_green","x":41.0,"y":46.0,"z":59.0}
{"name":"super_sam:clay_dark_green","x":41.0,"y":47.0,"z":59.0}
{"name":"super_sam:clay_dark_green","x":42.0,"y":46.0,"z":59.0}
{"name":"super_sam:clay_dark_green","x":42.0,"y":47.0,"z":59.0}
{"name":"super_sam:clay_dark_green","x":43.0,"y":46.0,"z":59.0}
{"name":"super_sam:clay_dark_green","x":43.0,"y":47.0,"z":59.0}
{"name":"super_sam:slope_clay_dark_green","param2":12.0,"x":44.0,"y":46.0,"z":59.0}
{"name":"super_sam:clay_dark_green","x":44.0,"y":47.0,"z":59.0}
{"name":"super_sam:slope_clay_dark_green","param2":11.0,"x":45.0,"y":47.0,"z":59.0}
{"name":"super_sam:slope_clay_dark_green","param2":9.0,"x":38.0,"y":47.0,"z":60.0}
{"name":"super_sam:slope_clay_dark_green","param2":9.0,"x":39.0,"y":46.0,"z":60.0}
{"name":"super_sam:clay_dark_green","param2":1.0,"x":39.0,"y":47.0,"z":60.0}
{"name":"super_sam:clay_dark_green","param2":1.0,"x":40.0,"y":46.0,"z":60.0}
{"name":"super_sam:clay_dark_green","param2":1.0,"x":40.0,"y":47.0,"z":60.0}
{"name":"super_sam:slope_clay_dark_green","param2":7.0,"x":41.0,"y":46.0,"z":60.0}
{"name":"super_sam:slope_clay_dark_green","param2":7.0,"x":41.0,"y":47.0,"z":60.0}
{"name":"super_sam:slope_clay_dark_green","param2":5.0,"x":43.0,"y":46.0,"z":60.0}
{"name":"super_sam:slope_clay_dark_green","param2":5.0,"x":43.0,"y":47.0,"z":60.0}
{"name":"super_sam:clay_dark_green","param2":3.0,"x":44.0,"y":46.0,"z":60.0}
{"name":"super_sam:clay_dark_green","param2":3.0,"x":44.0,"y":47.0,"z":60.0}
{"name":"super_sam:slope_clay_dark_green","param2":12.0,"x":45.0,"y":46.0,"z":60.0}
{"name":"super_sam:clay_dark_green","param2":11.0,"x":45.0,"y":47.0,"z":60.0}
{"name":"super_sam:slope_clay_dark_green","param2":12.0,"x":46.0,"y":47.0,"z":60.0}
{"name":"super_sam:clay_dark_green","param2":1.0,"x":38.0,"y":47.0,"z":61.0}
{"name":"super_sam:clay_dark_green","param2":1.0,"x":39.0,"y":46.0,"z":61.0}
{"name":"super_sam:clay_dark_green","param2":1.0,"x":39.0,"y":47.0,"z":61.0}
{"name":"super_sam:slope_clay_dark_green","param2":14.0,"x":40.0,"y":46.0,"z":61.0}
{"name":"super_sam:slope_clay_dark_green","param2":14.0,"x":40.0,"y":47.0,"z":61.0}
{"name":"super_sam:slope_clay_dark_green","param2":18.0,"x":44.0,"y":46.0,"z":61.0}
{"name":"super_sam:slope_clay_dark_green","param2":18.0,"x":44.0,"y":47.0,"z":61.0}
{"name":"super_sam:clay_dark_green","param2":3.0,"x":45.0,"y":46.0,"z":61.0}
{"name":"super_sam:clay_dark_green","param2":3.0,"x":45.0,"y":47.0,"z":61.0}
{"name":"super_sam:clay_dark_green","param2":3.0,"x":46.0,"y":47.0,"z":61.0}
{"name":"super_sam:clay_dark_green","param2":1.0,"x":38.0,"y":47.0,"z":62.0}
{"name":"super_sam:clay_dark_green","param2":1.0,"x":39.0,"y":46.0,"z":62.0}
{"name":"super_sam:clay_dark_green","param2":1.0,"x":39.0,"y":47.0,"z":62.0}
{"name":"super_sam:clay_dark_green","param2":3.0,"x":45.0,"y":46.0,"z":62.0}
{"name":"super_sam:clay_dark_green","param2":3.0,"x":45.0,"y":47.0,"z":62.0}
{"name":"super_sam:clay_dark_green","param2":3.0,"x":46.0,"y":47.0,"z":62.0}
{"name":"super_sam:clay_dark_green","param2":1.0,"x":38.0,"y":47.0,"z":63.0}
{"name":"super_sam:clay_dark_green","param2":1.0,"x":39.0,"y":46.0,"z":63.0}
{"name":"super_sam:clay_dark_green","param2":1.0,"x":39.0,"y":47.0,"z":63.0}
{"name":"super_sam:slope_clay_dark_green","param2":11.0,"x":40.0,"y":46.0,"z":63.0}
{"name":"super_sam:slope_clay_dark_green","param2":11.0,"x":40.0,"y":47.0,"z":63.0}
{"name":"super_sam:slope_clay_dark_green","param2":9.0,"x":44.0,"y":46.0,"z":63.0}
{"name":"super_sam:slope_clay_dark_green","param2":9.0,"x":44.0,"y":47.0,"z":63.0}
{"name":"super_sam:clay_dark_green","param2":3.0,"x":45.0,"y":46.0,"z":63.0}
{"name":"super_sam:clay_dark_green","param2":3.0,"x":45.0,"y":47.0,"z":63.0}
{"name":"super_sam:clay_dark_green","param2":3.0,"x":46.0,"y":47.0,"z":63.0}
{"name":"super_sam:slope_clay_dark_green","param2":5.0,"x":38.0,"y":47.0,"z":64.0}
{"name":"super_sam:slope_clay_dark_green","param2":5.0,"x":39.0,"y":46.0,"z":64.0}
{"name":"super_sam:clay_dark_green","param2":1.0,"x":39.0,"y":47.0,"z":64.0}
{"name":"super_sam:clay_dark_green","param2":2.0,"x":40.0,"y":46.0,"z":64.0}
{"name":"super_sam:clay_dark_green","param2":2.0,"x":40.0,"y":47.0,"z":64.0}
{"name":"super_sam:slope_clay_dark_green","param2":12.0,"x":41.0,"y":46.0,"z":64.0}
{"name":"super_sam:slope_clay_dark_green","param2":12.0,"x":41.0,"y":47.0,"z":64.0}
{"name":"super_sam:slope_clay_dark_green","param2":16.0,"x":43.0,"y":46.0,"z":64.0}
{"name":"super_sam:slope_clay_dark_green","param2":16.0,"x":43.0,"y":47.0,"z":64.0}
{"name":"super_sam:clay_dark_green","param2":3.0,"x":44.0,"y":46.0,"z":64.0}
{"name":"super_sam:clay_dark_green","param2":3.0,"x":44.0,"y":47.0,"z":64.0}
{"name":"super_sam:slope_clay_dark_green","param2":7.0,"x":45.0,"y":46.0,"z":64.0}
{"name":"super_sam:clay_dark_green","param2":3.0,"x":45.0,"y":47.0,"z":64.0}
{"name":"super_sam:slope_clay_dark_green","param2":7.0,"x":46.0,"y":47.0,"z":64.0}
{"name":"super_sam:slope_clay_dark_green","param2":5.0,"x":39.0,"y":47.0,"z":65.0}
{"name":"super_sam:slope_clay_dark_green","param2":18.0,"x":40.0,"y":46.0,"z":65.0}
{"name":"super_sam:clay_dark_green","param2":2.0,"x":40.0,"y":47.0,"z":65.0}
{"name":"super_sam:clay_dark_green","param2":2.0,"x":41.0,"y":46.0,"z":65.0}
{"name":"super_sam:clay_dark_green","param2":2.0,"x":41.0,"y":47.0,"z":65.0}
{"name":"super_sam:clay_dark_green","param2":2.0,"x":42.0,"y":46.0,"z":65.0}
{"name":"super_sam:clay_dark_green","param2":1.0,"x":42.0,"y":47.0,"z":65.0}
{"name":"super_sam:clay_dark_green","param2":2.0,"x":43.0,"y":46.0,"z":65.0}
{"name":"super_sam:clay_dark_green","param2":2.0,"x":43.0,"y":47.0,"z":65.0}
{"name":"super_sam:slope_clay_dark_green","param2":14.0,"x":44.0,"y":46.0,"z":65.0}
{"name":"super_sam:clay_dark_green","param2":2.0,"x":44.0,"y":47.0,"z":65.0}
{"name":"super_sam:slope_clay_dark_green","param2":7.0,"x":45.0,"y":47.0,"z":65.0}
{"name":"super_sam:slope_clay_dark_green","param2":18.0,"x":40.0,"y":47.0,"z":66.0}
{"name":"super_sam:clay_dark_green","param2":2.0,"x":41.0,"y":47.0,"z":66.0}
{"name":"super_sam:clay_dark_green","param2":2.0,"x":42.0,"y":47.0,"z":66.0}
{"name":"super_sam:clay_dark_green","param2":2.0,"x":43.0,"y":47.0,"z":66.0}
{"name":"super_sam:slope_clay_dark_green","param2":14.0,"x":44.0,"y":47.0,"z":66.0}
